1101_hw1/alu.v
module alu (
    input                i_clk,
    input                i_rst_n,
    input                i_valid,
    input  signed [11:0] i_data_a,
    input  signed [11:0] i_data_b,
    input         [ 2:0] i_inst,
    output               o_valid,
    output        [11:0] o_data,
    output               o_overflow
);

  // ---------------------------------------------------------------------------
  // Wires and Registers
  // ---------------------------------------------------------------------------
  reg [11:0] o_data_w, o_data_r;
  reg o_valid_w, o_valid_r;
  reg o_overflow_w, o_overflow_r;
  reg signed [11:0] abs_a_r, abs_b_r;
  reg signed [12:0] mean_r;
  reg signed [12:0] sum_r;
  reg signed [12:0] diff_r;
  reg signed [23:0] mult_result_r;
  reg signed [23:0] mac_mult_result_r;
  reg signed [23:0] fixed_format_r;
  reg signed [23:0] mac_fixed_format_r;
  reg signed [24:0] prev_accumulator_r;
  reg signed [24:0] accumulator_r;
  reg signed [24:0] rounded_r;
  reg signed [24:0] mac_rounded_r;


  // ---- Add your own wires and registers here if needed ---- //


  // ---------------------------------------------------------------------------
  // Continuous Assignment
  // ---------------------------------------------------------------------------
  assign o_valid = o_valid_r;
  assign o_data = o_data_r;
  assign o_overflow = o_overflow_r;
  // ---- Add your own wire data assignments here if needed ---- //


  // ---------------------------------------------------------------------------
  // Combinational Block
  // ---------------------------------------------------------------------------
  // ---- Write your conbinational block design here ---- //

  always @(*) begin

    o_valid_w = 1'b0;
    o_overflow_w = 1'b0;

    if (i_valid) begin

      prev_accumulator_r = 25'b0;

      case (i_inst)
        3'b000: begin
          sum_r = i_data_a + i_data_b;
          o_data_w = sum_r[11:0];
          o_valid_w = 1'b1;
          o_overflow_w = (i_data_a[11] == i_data_b[11]) && (sum_r[11] != i_data_a[11]);
        end  // ADD

        3'b001: begin
          diff_r = i_data_a - i_data_b;
          o_data_w = diff_r[11:0];
          o_valid_w = 1'b1;
          o_overflow_w = (i_data_a[11] != i_data_b[11]) && (i_data_a[11] != diff_r[11]);
        end  // SUBTRACT

        3'b010: begin
          mult_result_r = i_data_a * i_data_b;
          rounded_r = mult_result_r + 25'd16;
          fixed_format_r = {{5{rounded_r[23]}}, rounded_r[23:5]};  //sign extend and shift by 5
          o_valid_w = 1'b1;
          o_overflow_w = ({12{fixed_format_r[11]}} != fixed_format_r[23:12]);
          o_data_w = fixed_format_r[11:0];
        end  // MULTIPLY

        3'b011: begin
          mac_mult_result_r = i_data_a * i_data_b;
	  mac_rounded_r = mac_mult_result_r + 25'd16;
          mac_fixed_format_r = {{5{mac_rounded_r[23]}}, mac_rounded_r[16:5]};
          accumulator_r = prev_accumulator_r + mac_fixed_format_r;
          o_data_w = accumulator_r[11:0];
          o_valid_w = 1'b1;
          o_overflow_w = ({12{mac_fixed_format_r[11]}} != mac_fixed_format_r[23:12]);
        end  // MAC

        3'b100: begin
          o_data_w  = ~(i_data_a ^ i_data_b);
          o_valid_w = 1'b1;
        end  // XNOR

        3'b101: begin
          o_data_w  = (i_data_a[11] == 0) ? i_data_a : 12'd0;
          o_valid_w = 1'b1;
        end  // ReLU

        3'b110: begin
          mean_r = i_data_a + i_data_b;
          o_data_w = mean_r >> 1;
          o_valid_w = 1'b1;
        end  // MEAN

        3'b111: begin
          abs_a_r   = (i_data_a[11] == 1'b1) ? (~i_data_a + 1) : i_data_a;
          abs_b_r   = (i_data_b[11] == 1'b1) ? (~i_data_b + 1) : i_data_b;
          o_data_w  = (abs_a_r > abs_b_r) ? abs_a_r : abs_b_r;
          o_valid_w = 1'b1;
        end  // ABSOLUTE MAX

        default: begin
          o_data_w = 12'b0;
          o_valid_w = 1'b0;
          o_overflow_w = 1'b0;
        end  // Default case

      endcase
    end
  end

  // ---------------------------------------------------------------------------
  // Sequential Block
  // ---------------------------------------------------------------------------
  // ---- Write your sequential block design here ---- //

  always @(negedge i_clk or negedge i_rst_n) begin
    if (!i_rst_n) begin
      o_data_r <= 0;
      o_overflow_r <= 0;
      o_valid_r <= 0;
      prev_accumulator_r <= 0;
    end else begin
      o_data_r <= o_data_w;
      o_overflow_r <= o_overflow_w;
      o_valid_r <= o_valid_w;
      prev_accumulator_r <= accumulator_r;
    end
  end
endmodule

1101_hw1/testbench.v
`timescale 1ns/1ps
`define CYCLE       10.0
`define RST_DELAY   2
`define MAX_CYCLE   100000

`ifdef I0
    `define Inst_I  "./pattern/INST0_I.dat"
    `define Inst_O  "./pattern/INST0_O.dat"
    `define PAT_NUM 20
`elsif I1
    `define Inst_I  "./pattern/INST1_I.dat"
    `define Inst_O  "./pattern/INST1_O.dat"
    `define PAT_NUM 20
`elsif I2
    `define Inst_I  "./pattern/INST2_I.dat"
    `define Inst_O  "./pattern/INST2_O.dat"
    `define PAT_NUM 20
`elsif I3
    `define Inst_I  "./pattern/INST3_I.dat"
    `define Inst_O  "./pattern/INST3_O.dat"
    `define PAT_NUM 5
`elsif I4
    `define Inst_I  "./pattern/INST4_I.dat"
    `define Inst_O  "./pattern/INST4_O.dat"
    `define PAT_NUM 20
`elsif I5
    `define Inst_I  "./pattern/INST5_I.dat"
    `define Inst_O  "./pattern/INST5_O.dat"
    `define PAT_NUM 20
`elsif I6
    `define Inst_I  "./pattern/INST6_I.dat"
    `define Inst_O  "./pattern/INST6_O.dat"
    `define PAT_NUM 20
`elsif I7
    `define Inst_I  "./pattern/INST7_I.dat"
    `define Inst_O  "./pattern/INST7_O.dat"
    `define PAT_NUM 20
`elsif I8
    `define Inst_I  "./pattern/INST8_I.dat"
    `define Inst_O  "./pattern/INST8_O.dat"
    `define PAT_NUM 20
`else
    `define Inst_I  ""
    `define Inst_O  ""
    `define PAT_NUM 0
`endif




module tb;

    parameter INT_W  = 7;
    parameter FRAC_W = 5;
    parameter INST_W = 3;
    parameter DATA_W = INT_W + FRAC_W;

    reg                      i_clk;
    reg                      i_rst_n;
    reg                      i_valid;
    reg  signed [DATA_W-1:0] i_data_a;
    reg  signed [DATA_W-1:0] i_data_b;
    reg         [INST_W-1:0] i_inst;
    wire                     o_valid;
    wire signed [DATA_W-1:0] o_data;
    wire                     o_overflow;
    integer            i;
    integer            j;
    integer error;

    reg [2*DATA_W+INST_W-1:0] inst_idata [0:`PAT_NUM-1];
    reg [(DATA_W+1)-1:0]      inst_odata [0:`PAT_NUM-1];

    reg signed [DATA_W-1:0] test_inA  ;
    reg signed [DATA_W-1:0] test_inB  ;
    reg        [INST_W-1:0] test_inst ;
    reg                     test_outO ;
    reg signed [DATA_W-1:0] test_outD ;


    initial begin
        $readmemb(`Inst_I, inst_idata);
        $readmemb(`Inst_O, inst_odata);
    end


    alu u_alu (
        .i_clk          (i_clk      ),
        .i_rst_n        (i_rst_n    ),
        .i_valid        (i_valid    ),
        .i_data_a       (i_data_a   ),
        .i_data_b       (i_data_b   ),
        .i_inst         (i_inst     ),
        .o_valid        (o_valid    ),
        .o_data         (o_data     ),
        .o_overflow     (o_overflow )    
    );

    initial i_clk = 0;
    always #(`CYCLE/2.0) i_clk = ~i_clk; 
    initial begin
        $dumpfile("tb.vcd");
        $dumpvars(0, tb);
    end

    initial begin
        i        = 0;
        i_rst_n  = 1;
        i_valid  = 0;
        i_data_a = 0;
        i_data_b = 0;
        i_inst   = 0;
        reset;

        while (i < `PAT_NUM) begin
            @(negedge i_clk);
            i_valid = $random;
	    if (i_valid) begin
            	i_data_a = inst_idata[i][DATA_W-1          : 0];
            	i_data_b = inst_idata[i][2*DATA_W-1        : DATA_W];
            	i_inst   = inst_idata[i][2*DATA_W+INST_W-1 : 2*DATA_W+INST_W-3];
            	i = i + 1;
	    end
        end
        @(negedge i_clk);
	i_valid = 0;
    end

    initial begin
        j = 0;
        error = 0;
        while (j < `PAT_NUM) begin
            @(negedge i_clk);
            if (o_valid) begin
                test_inA  =  inst_idata[j][DATA_W-1          : 0     ];
                test_inB  =  inst_idata[j][2*DATA_W-1        : DATA_W];
                test_inst =  inst_idata[j][2*DATA_W+INST_W-1 : 2*DATA_W+INST_W-3];
                test_outO =  inst_odata[j][DATA_W];
                test_outD =  inst_odata[j][DATA_W-1          : 0     ];
                if (test_outO !== o_overflow) begin
                    $display (
                        "Test[%d]: Error! Inst=%b, A=%b, B=%b, Out=(%b, %b), yours=(%b, %b)", 
                        j, test_inst, test_inA, test_inB, test_outO, test_outD, o_overflow, o_data
                    );
                    error = error+1;
                end else if (test_outO == 0 && test_outD !== o_data) begin
                    $display (
                        "Test[%d]: Error! Inst=%b, A=%b, B=%b, Out=(%b, %b), yours=(%b, %b)", 
                        j, test_inst, test_inA, test_inB, test_outO, test_outD, o_overflow, o_data
                    );      
                    error = error+1;        
                end else if ((test_outD == o_data || test_outO !== 0) && test_outO == o_overflow) begin
                     $display("Test[%d]: Correct!", j);
                end else begin
                    $display("Test[%d]: Unknown output!!, Out=(%b, %b), yours=(%b, %b)", j, test_outO, test_outD, o_overflow, o_data);
                    error = error+1;
                end
                j = j + 1;
            end
        end

        $display("Pattern: ", `Inst_I);

        if(error == 0) begin
            $display("----------------------------------------------");
            $display("-                 ALL PASS!                  -");
            $display("----------------------------------------------");
        end else begin
            $display("----------------------------------------------");
            $display("  Wrong! Total error: %d                      ", error);
            $display("----------------------------------------------");
        end
        # ( 2 * `CYCLE);
        $finish;
    end

    initial begin
        # (`MAX_CYCLE * `CYCLE);
        $display("----------------------------------------------");
        $display("Latency of your design is over 100000 cycles!!");
        $display("----------------------------------------------");
        $finish;
    end

    task reset; begin
        # ( 0.25 * `CYCLE);
        i_rst_n = 0;    
        # ((`RST_DELAY) * `CYCLE);
        i_rst_n = 1;    
    end endtask

endmodule

1101_hw1/tb.vcd
$date
    Feb  5, 2026  18:07:18
$end
$version
    TOOL:	xmsim(64)	24.03-s013
$end
$timescale
    1 ps
$end

$scope module tb $end
$var parameter 32 !    INT_W $end
$var parameter 32 "    FRAC_W $end
$var parameter 32 #    INST_W $end
$var parameter 32 $    DATA_W $end
$var reg       1 %    i_clk $end
$var reg       1 &    i_rst_n $end
$var reg       1 '    i_valid $end
$var reg      12 (    i_data_a [11:0] $end
$var reg      12 )    i_data_b [11:0] $end
$var reg       3 *    i_inst [2:0] $end
$var wire      1 +    o_valid  $end
$var wire     12 ,    o_data [11:0] $end
$var wire      1 -    o_overflow  $end
$var integer  32 .    i $end
$var integer  32 /    j $end
$var integer  32 0    error $end
$var reg      27 1    inst_idata[0] [26:0] $end
$var reg      27 2    inst_idata[1] [26:0] $end
$var reg      27 3    inst_idata[2] [26:0] $end
$var reg      27 4    inst_idata[3] [26:0] $end
$var reg      27 5    inst_idata[4] [26:0] $end
$var reg      13 6    inst_odata[0] [12:0] $end
$var reg      13 7    inst_odata[1] [12:0] $end
$var reg      13 8    inst_odata[2] [12:0] $end
$var reg      13 9    inst_odata[3] [12:0] $end
$var reg      13 :    inst_odata[4] [12:0] $end
$var reg      12 ;    test_inA [11:0] $end
$var reg      12 <    test_inB [11:0] $end
$var reg       3 =    test_inst [2:0] $end
$var reg       1 >    test_outO $end
$var reg      12 ?    test_outD [11:0] $end

$scope module u_alu $end
$var wire      1 @    i_clk  $end
$var wire      1 A    i_rst_n  $end
$var wire      1 B    i_valid  $end
$var wire     12 C    i_data_a [11:0] $end
$var wire     12 D    i_data_b [11:0] $end
$var wire      3 E    i_inst [2:0] $end
$var wire      1 +    o_valid  $end
$var wire     12 ,    o_data [11:0] $end
$var wire      1 -    o_overflow  $end
$var reg      12 F    o_data_w [11:0] $end
$var reg      12 G    o_data_r [11:0] $end
$var reg       1 H    o_valid_w $end
$var reg       1 I    o_valid_r $end
$var reg       1 J    o_overflow_w $end
$var reg       1 K    o_overflow_r $end
$var reg      12 L    abs_a_r [11:0] $end
$var reg      12 M    abs_b_r [11:0] $end
$var reg      13 N    mean_r [12:0] $end
$var reg      13 O    sum_r [12:0] $end
$var reg      13 P    diff_r [12:0] $end
$var reg      24 Q    mult_result_r [23:0] $end
$var reg      24 R    mac_mult_result_r [23:0] $end
$var reg      24 S    fixed_format_r [23:0] $end
$var reg      24 T    mac_fixed_format_r [23:0] $end
$var reg      25 U    prev_accumulator_r [24:0] $end
$var reg      25 V    accumulator_r [24:0] $end
$var reg      25 W    rounded_r [24:0] $end
$var reg      25 X    mac_rounded_r [24:0] $end
$upscope $end

$upscope $end

$enddefinitions $end
$dumpvars
b1100 $
b11 #
b101 "
b111 !
0%
1&
0'
b0 (
b0 )
b0 *
x+
bx ,
x-
b0 .
b0 /
b0 0
b11000011000001000011001100 1
b11111101001001000011001010 2
b11111100101101000011000000 3
b11000010010100111100010001 4
b11000010011010000010111010 5
b10011001110 6
b1001011 7
b101101011001 8
b1011100001000 9
b1101010000111 :
bx ;
bx <
bx =
x>
bx ?
0@
1A
0B
b0 C
b0 D
b0 E
bx F
bx G
0H
xI
0J
xK
bx L
bx M
bx N
bx O
bx P
bx Q
bx R
bx S
bx T
bx U
bx V
bx W
bx X
$end
#2500
0&
0A
b0 G
0K
0I
b0 U
0+
0-
b0 ,
#5000
1%
1@
#10000
0%
0@
#15000
1%
1@
#20000
0%
0@
#22500
1&
1A
#25000
1%
1@
#30000
0%
0@
bx G
bx U
bx ,
#35000
1%
1@
#40000
0%
1'
b11001100 (
b11000001 )
b11 *
b1 .
b11 E
b11000001 D
b11001100 C
1B
0@
b0 U
b1001100111001100 R
b1001100111011100 X
b10011001110 T
b10011001110 V
b10011001110 F
1H
b10011001110 G
1I
b10011001110 U
0H
b0 U
1H
1+
b10011001110 ,
#45000
1%
1@
#50000
0%
b11001100 ;
b11000001 <
b11 =
0>
b10011001110 ?
b1 /
b11001010 (
b111101001001 )
b10 .
b111101001001 D
b11001010 C
0@
0H
b111111110110111110011010 R
b111111110110111110101010 X
b11111101101111101 T
b11111101101111101 V
b101101111101 F
1H
1J
b101101111101 G
1K
b11111101101111101 U
0H
0J
b0 U
1H
1J
1-
b101101111101 ,
#55000
1%
1@
#60000
0%
b11001010 ;
b111101001001 <
b1001011 ?
b1 0
b10 /
b11000000 (
b111100101101 )
b11 .
b111100101101 D
b11000000 C
0@
0H
0J
b111111110110000111000000 R
b111111110110000111010000 X
b11111101100001110 T
b11111101100001110 V
b101100001110 F
1H
1J
b101100001110 G
b11111101100001110 U
0H
0J
b0 U
1H
1J
b101100001110 ,
#65000
1%
1@
#70000
0%
b11000000 ;
b111100101101 <
b101101011001 ?
b10 0
b11 /
b111100010001 (
b10010100 )
b100 .
b10010100 D
b111100010001 C
0@
0H
0J
b111111110111010111010100 R
b111111110111010111100100 X
b11111101110101111 T
b11111101110101111 V
b101110101111 F
1H
1J
b101110101111 G
b11111101110101111 U
0H
0J
b0 U
1H
1J
b101110101111 ,
#75000
1%
1@
#80000
0%
b111100010001 ;
b10010100 <
1>
b11100001000 ?
b100 /
b10111010 (
b10011010 )
b101 .
b10011010 D
b10111010 C
0@
0H
0J
b110111111100100 R
b110111111110100 X
b1101111111 T
b1101111111 V
b1101111111 F
1H
b1101111111 G
0K
b1101111111 U
0H
b0 U
1H
0-
b1101111111 ,
#85000
1%
1@
#90000
0%
b10111010 ;
b10011010 <
b101010000111 ?
b11 0
b101 /
0'
0B
0@
0H
0I
b1101111111 U
0+
