1101_hw1/alu.v
module alu (
    input                i_clk,
    input                i_rst_n,
    input                i_valid,
    input  signed [11:0] i_data_a,
    input  signed [11:0] i_data_b,
    input         [ 2:0] i_inst,
    output               o_valid,
    output        [11:0] o_data,
    output               o_overflow
);

  // ---------------------------------------------------------------------------
  // Wires and Registers
  // ---------------------------------------------------------------------------
  reg [11:0] o_data_w, o_data_r;
  reg o_valid_w, o_valid_r;
  reg o_overflow_w, o_overflow_r;
  reg prev_overflow_r;
  reg mac_mult_overflow_w;
  reg mac_add_overflow_w;
  reg mac_overflow_res_w;
  reg signed [11:0] abs_a_w, abs_b_w;
  reg signed [12:0] mean_w;
  reg signed [12:0] sum_w;
  reg signed [12:0] diff_w;
  reg signed [23:0] mult_result_w;
  reg signed [23:0] mac_mult_result_w;
  reg signed [23:0] fixed_format_w;
  reg signed [23:0] mac_fixed_format_w;
  reg signed [12:0] prev_accumulator_r;
  reg signed [12:0] accumulator_w;
  reg signed [24:0] rounded_w;
  reg signed [24:0] mac_rounded_w;
  // ---- Add your own wires and registers here if needed ---- //


  // ---------------------------------------------------------------------------
  // Continuous Assignment
  // ---------------------------------------------------------------------------
  assign o_valid = o_valid_r;
  assign o_data = o_data_r;
  assign o_overflow = o_overflow_r;
  // ---- Add your own wire data assignments here if needed ---- //


  // ---------------------------------------------------------------------------
  // Combinational Block
  // ---------------------------------------------------------------------------
  // ---- Write your conbinational block design here ---- //

  always @(*) begin

    o_valid_w = 1'b0;
    o_overflow_w = 1'b0;
    mac_overflow_res_w = 1'b0;
    accumulator_w = prev_accumulator_r;

    if (i_valid) begin

      o_valid_w = 1'b1;
      if (i_inst != 3'b011) begin
	accumulator_w = 13'b0;
      end


        case (i_inst)
          3'b000: begin
            sum_w = i_data_a + i_data_b;
            o_data_w = sum_w[11:0];
            o_overflow_w = (i_data_a[11] == i_data_b[11]) && (sum_w[11] != i_data_a[11]);
          end  // ADD

          3'b001: begin
            diff_w = i_data_a - i_data_b;
            o_data_w = diff_w[11:0];
            o_overflow_w = (i_data_a[11] != i_data_b[11]) && (i_data_a[11] != diff_w[11]);
          end  // SUBTRACT

          3'b010: begin
            mult_result_w = i_data_a * i_data_b;
            rounded_w = mult_result_w + 25'd16;
            fixed_format_w = {{5{rounded_w[23]}}, rounded_w[23:5]};  //sign extend and shift by 5
            o_overflow_w = ({12{fixed_format_w[11]}} != fixed_format_w[23:12]);
            o_data_w = fixed_format_w[11:0];
          end  // MULTIPLY

          3'b011: begin
            mac_mult_result_w = i_data_a * i_data_b;
            mac_rounded_w = mac_mult_result_w + 25'd16;
            mac_fixed_format_w = {{5{mac_rounded_w[23]}}, mac_rounded_w[23:5]};
            accumulator_w = prev_accumulator_r + mac_fixed_format_w;
            o_data_w = accumulator_w[11:0];
            mac_overflow_res_w = (({12{mac_fixed_format_w[11]}} != mac_fixed_format_w[23:12]) || ((prev_accumulator_r[12] == mac_fixed_format_w[11]) && (accumulator_w[11] != mac_fixed_format_w[11])));
            o_overflow_w = prev_overflow_r || mac_overflow_res_w;
          end  // MAC

          3'b100: begin
            o_data_w = ~(i_data_a ^ i_data_b);
          end  // XNOR

          3'b101: begin
            o_data_w = (i_data_a[11] == 0) ? i_data_a : 12'd0;
          end  // ReLU

          3'b110: begin
            mean_w   = i_data_a + i_data_b;
            o_data_w = mean_w >> 1;
          end  // MEAN

          3'b111: begin
            abs_a_w  = (i_data_a[11] == 1'b1) ? (~i_data_a + 1) : i_data_a;
            abs_b_w  = (i_data_b[11] == 1'b1) ? (~i_data_b + 1) : i_data_b;
            o_data_w = (abs_a_w > abs_b_w) ? abs_a_w : abs_b_w;
          end  // ABSOLUTE MAX

          default: begin
            o_data_w = 12'b0;
            o_valid_w = 1'b0;
            o_overflow_w = 1'b0;
          end  // Default case

        endcase
    end
  end

  // ---------------------------------------------------------------------------
  // Sequential Block
  // ---------------------------------------------------------------------------
  // ---- Write your sequential block design here ---- //

  always @(negedge i_clk or negedge i_rst_n) begin
    if (!i_rst_n) begin
      o_data_r <= 0;
      o_overflow_r <= 0;
      o_valid_r <= 0;
      prev_accumulator_r <= 0;
      prev_overflow_r <= 0;
    end else begin
      o_data_r <= o_data_w;
      o_overflow_r <= o_overflow_w;
      o_valid_r <= o_valid_w;
      prev_accumulator_r <= accumulator_w;
      prev_overflow_r <= mac_overflow_res_w;
    end
  end
endmodule

1101_hw1/testbench.v
`timescale 1ns/1ps
`define CYCLE       10.0
`define RST_DELAY   2
`define MAX_CYCLE   100000

`ifdef I0
    `define Inst_I  "./pattern/INST0_I.dat"
    `define Inst_O  "./pattern/INST0_O.dat"
    `define PAT_NUM 20
`elsif I1
    `define Inst_I  "./pattern/INST1_I.dat"
    `define Inst_O  "./pattern/INST1_O.dat"
    `define PAT_NUM 20
`elsif I2
    `define Inst_I  "./pattern/INST2_I.dat"
    `define Inst_O  "./pattern/INST2_O.dat"
    `define PAT_NUM 20
`elsif I3
    `define Inst_I  "./pattern/INST3_I.dat"
    `define Inst_O  "./pattern/INST3_O.dat"
    `define PAT_NUM 5
`elsif I4
    `define Inst_I  "./pattern/INST4_I.dat"
    `define Inst_O  "./pattern/INST4_O.dat"
    `define PAT_NUM 20
`elsif I5
    `define Inst_I  "./pattern/INST5_I.dat"
    `define Inst_O  "./pattern/INST5_O.dat"
    `define PAT_NUM 20
`elsif I6
    `define Inst_I  "./pattern/INST6_I.dat"
    `define Inst_O  "./pattern/INST6_O.dat"
    `define PAT_NUM 20
`elsif I7
    `define Inst_I  "./pattern/INST7_I.dat"
    `define Inst_O  "./pattern/INST7_O.dat"
    `define PAT_NUM 20
`elsif I8
    `define Inst_I  "./pattern/INST8_I.dat"
    `define Inst_O  "./pattern/INST8_O.dat"
    `define PAT_NUM 20
`else
    `define Inst_I  ""
    `define Inst_O  ""
    `define PAT_NUM 0
`endif




module tb;

    parameter INT_W  = 7;
    parameter FRAC_W = 5;
    parameter INST_W = 3;
    parameter DATA_W = INT_W + FRAC_W;

    reg                      i_clk;
    reg                      i_rst_n;
    reg                      i_valid;
    reg  signed [DATA_W-1:0] i_data_a;
    reg  signed [DATA_W-1:0] i_data_b;
    reg         [INST_W-1:0] i_inst;
    wire                     o_valid;
    wire signed [DATA_W-1:0] o_data;
    wire                     o_overflow;
    integer            i;
    integer            j;
    integer error;

    reg [2*DATA_W+INST_W-1:0] inst_idata [0:`PAT_NUM-1];
    reg [(DATA_W+1)-1:0]      inst_odata [0:`PAT_NUM-1];

    reg signed [DATA_W-1:0] test_inA  ;
    reg signed [DATA_W-1:0] test_inB  ;
    reg        [INST_W-1:0] test_inst ;
    reg                     test_outO ;
    reg signed [DATA_W-1:0] test_outD ;


    initial begin
        $readmemb(`Inst_I, inst_idata);
        $readmemb(`Inst_O, inst_odata);
    end


    alu u_alu (
        .i_clk          (i_clk      ),
        .i_rst_n        (i_rst_n    ),
        .i_valid        (i_valid    ),
        .i_data_a       (i_data_a   ),
        .i_data_b       (i_data_b   ),
        .i_inst         (i_inst     ),
        .o_valid        (o_valid    ),
        .o_data         (o_data     ),
        .o_overflow     (o_overflow )    
    );

    initial i_clk = 0;
    always #(`CYCLE/2.0) i_clk = ~i_clk; 
    initial begin
        $dumpfile("tb.vcd");
        $dumpvars(0, tb);
    end

    initial begin
        i        = 0;
        i_rst_n  = 1;
        i_valid  = 0;
        i_data_a = 0;
        i_data_b = 0;
        i_inst   = 0;
        reset;

        while (i < `PAT_NUM) begin
            @(negedge i_clk);
            i_valid = $random;
	    if (i_valid) begin
            	i_data_a = inst_idata[i][DATA_W-1          : 0];
            	i_data_b = inst_idata[i][2*DATA_W-1        : DATA_W];
            	i_inst   = inst_idata[i][2*DATA_W+INST_W-1 : 2*DATA_W+INST_W-3];
            	i = i + 1;
	    end
        end
        @(negedge i_clk);
	i_valid = 0;
    end

    initial begin
        j = 0;
        error = 0;
        while (j < `PAT_NUM) begin
            @(negedge i_clk);
            if (o_valid) begin
                test_inA  =  inst_idata[j][DATA_W-1          : 0     ];
                test_inB  =  inst_idata[j][2*DATA_W-1        : DATA_W];
                test_inst =  inst_idata[j][2*DATA_W+INST_W-1 : 2*DATA_W+INST_W-3];
                test_outO =  inst_odata[j][DATA_W];
                test_outD =  inst_odata[j][DATA_W-1          : 0     ];
                if (test_outO !== o_overflow) begin
                    $display (
                        "Test[%d]: Error! Inst=%b, A=%b, B=%b, Out=(%b, %b), yours=(%b, %b)", 
                        j, test_inst, test_inA, test_inB, test_outO, test_outD, o_overflow, o_data
                    );
                    error = error+1;
                end else if (test_outO == 0 && test_outD !== o_data) begin
                    $display (
                        "Test[%d]: Error! Inst=%b, A=%b, B=%b, Out=(%b, %b), yours=(%b, %b)", 
                        j, test_inst, test_inA, test_inB, test_outO, test_outD, o_overflow, o_data
                    );      
                    error = error+1;        
                end else if ((test_outD == o_data || test_outO !== 0) && test_outO == o_overflow) begin
                     $display("Test[%d]: Correct!", j);
                end else begin
                    $display("Test[%d]: Unknown output!!, Out=(%b, %b), yours=(%b, %b)", j, test_outO, test_outD, o_overflow, o_data);
                    error = error+1;
                end
                j = j + 1;
            end
        end

        $display("Pattern: ", `Inst_I);

        if(error == 0) begin
            $display("----------------------------------------------");
            $display("-                 ALL PASS!                  -");
            $display("----------------------------------------------");
        end else begin
            $display("----------------------------------------------");
            $display("  Wrong! Total error: %d                      ", error);
            $display("----------------------------------------------");
        end
        # ( 2 * `CYCLE);
        $finish;
    end

    initial begin
        # (`MAX_CYCLE * `CYCLE);
        $display("----------------------------------------------");
        $display("Latency of your design is over 100000 cycles!!");
        $display("----------------------------------------------");
        $finish;
    end

    task reset; begin
        # ( 0.25 * `CYCLE);
        i_rst_n = 0;    
        # ((`RST_DELAY) * `CYCLE);
        i_rst_n = 1;    
    end endtask

endmodule

1101_hw1/tb.vcd
$date
    Feb 10, 2026  10:51:27
$end
$version
    TOOL:	xmsim(64)	24.03-s013
$end
$timescale
    1 ps
$end

$scope module tb $end
$var parameter 32 !    INT_W $end
$var parameter 32 "    FRAC_W $end
$var parameter 32 #    INST_W $end
$var parameter 32 $    DATA_W $end
$var reg       1 %    i_clk $end
$var reg       1 &    i_rst_n $end
$var reg       1 '    i_valid $end
$var reg      12 (    i_data_a [11:0] $end
$var reg      12 )    i_data_b [11:0] $end
$var reg       3 *    i_inst [2:0] $end
$var wire      1 +    o_valid  $end
$var wire     12 ,    o_data [11:0] $end
$var wire      1 -    o_overflow  $end
$var integer  32 .    i $end
$var integer  32 /    j $end
$var integer  32 0    error $end
$var reg      27 1    inst_idata[0] [26:0] $end
$var reg      27 2    inst_idata[1] [26:0] $end
$var reg      27 3    inst_idata[2] [26:0] $end
$var reg      27 4    inst_idata[3] [26:0] $end
$var reg      27 5    inst_idata[4] [26:0] $end
$var reg      27 6    inst_idata[5] [26:0] $end
$var reg      27 7    inst_idata[6] [26:0] $end
$var reg      27 8    inst_idata[7] [26:0] $end
$var reg      27 9    inst_idata[8] [26:0] $end
$var reg      27 :    inst_idata[9] [26:0] $end
$var reg      27 ;    inst_idata[10] [26:0] $end
$var reg      27 <    inst_idata[11] [26:0] $end
$var reg      27 =    inst_idata[12] [26:0] $end
$var reg      27 >    inst_idata[13] [26:0] $end
$var reg      27 ?    inst_idata[14] [26:0] $end
$var reg      27 @    inst_idata[15] [26:0] $end
$var reg      27 A    inst_idata[16] [26:0] $end
$var reg      27 B    inst_idata[17] [26:0] $end
$var reg      27 C    inst_idata[18] [26:0] $end
$var reg      27 D    inst_idata[19] [26:0] $end
$var reg      13 E    inst_odata[0] [12:0] $end
$var reg      13 F    inst_odata[1] [12:0] $end
$var reg      13 G    inst_odata[2] [12:0] $end
$var reg      13 H    inst_odata[3] [12:0] $end
$var reg      13 I    inst_odata[4] [12:0] $end
$var reg      13 J    inst_odata[5] [12:0] $end
$var reg      13 K    inst_odata[6] [12:0] $end
$var reg      13 L    inst_odata[7] [12:0] $end
$var reg      13 M    inst_odata[8] [12:0] $end
$var reg      13 N    inst_odata[9] [12:0] $end
$var reg      13 O    inst_odata[10] [12:0] $end
$var reg      13 P    inst_odata[11] [12:0] $end
$var reg      13 Q    inst_odata[12] [12:0] $end
$var reg      13 R    inst_odata[13] [12:0] $end
$var reg      13 S    inst_odata[14] [12:0] $end
$var reg      13 T    inst_odata[15] [12:0] $end
$var reg      13 U    inst_odata[16] [12:0] $end
$var reg      13 V    inst_odata[17] [12:0] $end
$var reg      13 W    inst_odata[18] [12:0] $end
$var reg      13 X    inst_odata[19] [12:0] $end
$var reg      12 Y    test_inA [11:0] $end
$var reg      12 Z    test_inB [11:0] $end
$var reg       3 [    test_inst [2:0] $end
$var reg       1 \    test_outO $end
$var reg      12 ]    test_outD [11:0] $end

$scope module u_alu $end
$var wire      1 ^    i_clk  $end
$var wire      1 _    i_rst_n  $end
$var wire      1 `    i_valid  $end
$var wire     12 a    i_data_a [11:0] $end
$var wire     12 b    i_data_b [11:0] $end
$var wire      3 c    i_inst [2:0] $end
$var wire      1 +    o_valid  $end
$var wire     12 ,    o_data [11:0] $end
$var wire      1 -    o_overflow  $end
$var reg      12 d    o_data_w [11:0] $end
$var reg      12 e    o_data_r [11:0] $end
$var reg       1 f    o_valid_w $end
$var reg       1 g    o_valid_r $end
$var reg       1 h    o_overflow_w $end
$var reg       1 i    o_overflow_r $end
$var reg       1 j    prev_overflow_r $end
$var reg       1 k    mac_mult_overflow_w $end
$var reg       1 l    mac_add_overflow_w $end
$var reg       1 m    mac_overflow_res_w $end
$var reg      12 n    abs_a_w [11:0] $end
$var reg      12 o    abs_b_w [11:0] $end
$var reg      13 p    mean_w [12:0] $end
$var reg      13 q    sum_w [12:0] $end
$var reg      13 r    diff_w [12:0] $end
$var reg      24 s    mult_result_w [23:0] $end
$var reg      24 t    mac_mult_result_w [23:0] $end
$var reg      24 u    fixed_format_w [23:0] $end
$var reg      24 v    mac_fixed_format_w [23:0] $end
$var reg      13 w    prev_accumulator_r [12:0] $end
$var reg      13 x    accumulator_w [12:0] $end
$var reg      25 y    rounded_w [24:0] $end
$var reg      25 z    mac_rounded_w [24:0] $end
$upscope $end

$upscope $end

$enddefinitions $end
$dumpvars
b1100 $
b11 #
b101 "
b111 !
0%
1&
0'
b0 (
b0 )
b0 *
x+
bx ,
x-
b0 .
b0 /
b0 0
b111011111110101011111011100 1
b111111111011000000000001111 2
b111100101011011110011011000 3
b111101011001100100011110111 4
b111001001100101111000011011 5
b111010001101111001101111110 6
b111100110101111100001101010 7
b111100110010100000100110010 8
b111111011111010000111111110 9
b111000010000001101001010001 :
b111100110011001101100000100 ;
b111000101001001100110011100 <
b111110010110000011110110000 =
b111111001100111011011010000 >
b111100101000001101010100111 ?
b111100100111010101011100100 @
b111000010111101100000000111 A
b111010000001100110011011101 B
b111100000000110001101001110 C
b111100100011101101010111011 D
b11111110101 E
b101000 F
b11010100101 G
b11100001001 H
b1001100101 I
b10001101111 J
b11110010110 K
b11001101100 L
b111111110 M
b10110101111 N
b11001100111 O
b11001100100 P
b11110110000 Q
b11011010000 R
b11010111111 S
b11011000110 T
b11111111001 U
b10000001100 V
b11111111010 W
b11011100011 X
bx Y
bx Z
bx [
x\
bx ]
0^
1_
0`
b0 a
b0 b
b0 c
bx d
bx e
0f
xg
0h
xi
xj
xk
xl
0m
bx n
bx o
bx p
bx q
bx r
bx s
bx t
bx u
bx v
bx w
bx x
bx y
bx z
$end
#2500
0&
0_
b0 e
0i
0g
b0 w
0j
b0 x
0+
0-
b0 ,
#5000
1%
1^
#10000
0%
0^
#15000
1%
1^
#20000
0%
0^
#22500
1&
1_
#25000
1%
1^
#30000
0%
0^
bx e
bx ,
#35000
1%
1^
#40000
0%
1'
b11111011100 (
b11111110101 )
b111 *
b1 .
b111 c
b11111110101 b
b11111011100 a
1`
0^
1f
b11111011100 n
b11111110101 o
b11111110101 d
b11111110101 e
1g
1+
b11111110101 ,
#45000
1%
1^
#50000
0%
b11111011100 Y
b11111110101 Z
b111 [
0\
b11111110101 ]
b1 /
b1111 (
b111111011000 )
b10 .
b111111011000 b
b1111 a
0^
0f
1f
b1111 n
b101000 o
b101000 d
b101000 e
b101000 ,
#55000
1%
1^
#60000
0%
b1111 Y
b111111011000 Z
b101000 ]
b10 /
b110011011000 (
b100101011011 )
b11 .
b100101011011 b
b110011011000 a
0^
0f
1f
b1100101000 n
b11010100101 o
b11010100101 d
b11010100101 e
b11010100101 ,
#65000
1%
1^
#70000
0%
b110011011000 Y
b100101011011 Z
b11010100101 ]
b11 /
b100011110111 (
b101011001100 )
b100 .
b101011001100 b
b100011110111 a
0^
0f
1f
b11100001001 n
b10100110100 o
b11100001001 d
b11100001001 e
b11100001001 ,
#75000
1%
1^
#80000
0%
b100011110111 Y
b101011001100 Z
b11100001001 ]
b100 /
b111000011011 (
b1001100101 )
b101 .
b1001100101 b
b111000011011 a
0^
0f
1f
b111100101 n
b1001100101 o
b1001100101 d
b1001100101 e
b1001100101 ,
#85000
1%
1^
#90000
0%
b111000011011 Y
b1001100101 Z
b1001100101 ]
b101 /
b1101111110 (
b10001101111 )
b110 .
b10001101111 b
b1101111110 a
0^
0f
1f
b1101111110 n
b10001101111 o
b10001101111 d
b10001101111 e
b10001101111 ,
#95000
1%
1^
#100000
0%
b1101111110 Y
b10001101111 Z
b10001101111 ]
b110 /
0'
0`
0^
0f
0g
0+
#105000
1%
1^
#110000
0%
1'
b100001101010 (
b100110101111 )
b111 .
b100110101111 b
b100001101010 a
1`
0^
1f
b11110010110 n
b11001010001 o
b11110010110 d
b11110010110 e
1g
1+
b11110010110 ,
#115000
1%
1^
#120000
0%
b100001101010 Y
b100110101111 Z
b11110010110 ]
b111 /
b100110010 (
b100110010100 )
b1000 .
b100110010100 b
b100110010 a
0^
0f
1f
b100110010 n
b11001101100 o
b11001101100 d
b11001101100 e
b11001101100 ,
#125000
1%
1^
#130000
0%
b100110010 Y
b100110010100 Z
b11001101100 ]
b1000 /
0'
0`
0^
0f
0g
0+
#135000
1%
1^
#140000
0%
1'
b111111110 (
b111011111010 )
b1001 .
b111011111010 b
b111111110 a
1`
0^
1f
b111111110 n
b100000110 o
b111111110 d
b111111110 e
1g
1+
b111111110 ,
#145000
1%
1^
#150000
0%
b111111110 Y
b111011111010 Z
b111111110 ]
b1001 /
b101001010001 (
b10000001 )
b1010 .
b10000001 b
b101001010001 a
0^
0f
1f
b10110101111 n
b10000001 o
b10110101111 d
b10110101111 e
b10110101111 ,
#155000
1%
1^
#160000
0%
b101001010001 Y
b10000001 Z
b10110101111 ]
b1010 /
0'
0`
0^
0f
0g
0+
#165000
1%
1^
#170000
0%
1'
b101100000100 (
b100110011001 )
b1011 .
b100110011001 b
b101100000100 a
1`
0^
1f
b10011111100 n
b11001100111 o
b11001100111 d
b11001100111 e
1g
1+
b11001100111 ,
#175000
1%
1^
#180000
0%
b101100000100 Y
b100110011001 Z
b11001100111 ]
b1011 /
0'
0`
0^
0f
0g
0+
#185000
1%
1^
#190000
0%
1'
b100110011100 (
b101001001 )
b1100 .
b101001001 b
b100110011100 a
1`
0^
1f
b11001100100 n
b101001001 o
b11001100100 d
b11001100100 e
1g
1+
b11001100100 ,
#195000
1%
1^
#200000
0%
b100110011100 Y
b101001001 Z
b11001100100 ]
b1100 /
0'
0`
0^
0f
0g
0+
#205000
1%
1^
#210000
0%
1'
b11110110000 (
b110010110000 )
b1101 .
b110010110000 b
b11110110000 a
1`
0^
1f
b11110110000 n
b1101010000 o
b11110110000 d
b11110110000 e
1g
1+
b11110110000 ,
#215000
1%
1^
#220000
0%
b11110110000 Y
b110010110000 Z
b11110110000 ]
b1101 /
b11011010000 (
b111001100111 )
b1110 .
b111001100111 b
b11011010000 a
0^
0f
1f
b11011010000 n
b110011001 o
b11011010000 d
b11011010000 e
b11011010000 ,
#225000
1%
1^
#230000
0%
b11011010000 Y
b111001100111 Z
b11011010000 ]
b1110 /
0'
0`
0^
0f
0g
0+
#235000
1%
1^
#240000
0%
1'
b101010100111 (
b100101000001 )
b1111 .
b100101000001 b
b101010100111 a
1`
0^
1f
b10101011001 n
b11010111111 o
b11010111111 d
b11010111111 e
1g
1+
b11010111111 ,
#245000
1%
1^
#250000
0%
b101010100111 Y
b100101000001 Z
b11010111111 ]
b1111 /
0'
0`
0^
0f
0g
0+
#255000
1%
1^
#260000
0%
0^
#265000
1%
1^
#270000
0%
0^
#275000
1%
1^
#280000
0%
1'
b101011100100 (
b100100111010 )
b10000 .
b100100111010 b
b101011100100 a
1`
0^
1f
b10100011100 n
b11011000110 o
b11011000110 d
b11011000110 e
1g
1+
b11011000110 ,
#285000
1%
1^
#290000
0%
b101011100100 Y
b100100111010 Z
b11011000110 ]
b10000 /
0'
0`
0^
0f
0g
0+
#295000
1%
1^
#300000
0%
1'
b100000000111 (
b10111101 )
b10001 .
b10111101 b
b100000000111 a
1`
0^
1f
b11111111001 n
b10111101 o
b11111111001 d
b11111111001 e
1g
1+
b11111111001 ,
#305000
1%
1^
#310000
0%
b100000000111 Y
b10111101 Z
b11111111001 ]
b10001 /
b110011011101 (
b10000001100 )
b10010 .
b10000001100 b
b110011011101 a
0^
0f
1f
b1100100011 n
b10000001100 o
b10000001100 d
b10000001100 e
b10000001100 ,
#315000
1%
1^
#320000
0%
b110011011101 Y
b10000001100 Z
b10000001100 ]
b10010 /
b1101001110 (
b100000000110 )
b10011 .
b100000000110 b
b1101001110 a
0^
0f
1f
b1101001110 n
b11111111010 o
b11111111010 d
b11111111010 e
b11111111010 ,
#325000
1%
1^
#330000
0%
b1101001110 Y
b100000000110 Z
b11111111010 ]
b10011 /
b101010111011 (
b100100011101 )
b10100 .
b100100011101 b
b101010111011 a
0^
0f
1f
b10101000101 n
b11011100011 o
b11011100011 d
b11011100011 e
b11011100011 ,
#335000
1%
1^
#340000
0%
b101010111011 Y
b100100011101 Z
b11011100011 ]
b10100 /
0'
0`
0^
0f
0g
0+
