1101_hw1/alu.v
module alu (
    input                i_clk,
    input                i_rst_n,
    input                i_valid,
    input  signed [11:0] i_data_a,
    input  signed [11:0] i_data_b,
    input         [ 2:0] i_inst,
    output               o_valid,
    output        [11:0] o_data,
    output               o_overflow
);

  // ---------------------------------------------------------------------------
  // Wires and Registers
  // ---------------------------------------------------------------------------
  reg [11:0] o_data_w, o_data_r;
  reg o_valid_w, o_valid_r;
  reg o_overflow_w, o_overflow_r;
  reg signed [11:0] abs_a_r, abs_b_r;
  reg signed [12:0] mean_r;
  reg signed [12:0] sum_r;
  reg signed [12:0] diff_r;
  reg signed [23:0] mult_result_r;
  reg signed [23:0] mac_mult_result_r;
  reg signed [23:0] fixed_format_r;
  reg signed [23:0] mac_fixed_format_r;
  reg signed [24:0] prev_accumulator_r;
  reg signed [24:0] accumulator_r;

  // ---- Add your own wires and registers here if needed ---- //


  // ---------------------------------------------------------------------------
  // Continuous Assignment
  // ---------------------------------------------------------------------------
  assign o_valid = o_valid_r;
  assign o_data = o_data_r;
  assign o_overflow = o_overflow_r;
  // ---- Add your own wire data assignments here if needed ---- //


  // ---------------------------------------------------------------------------
  // Combinational Block
  // ---------------------------------------------------------------------------
  // ---- Write your conbinational block design here ---- //

  always @(*) begin

    o_valid_w = 1'b0;
    o_overflow_w = 1'b0;

    if (i_valid) begin

      prev_accumulator_r = 25'b0;

      case (i_inst)
        3'b000: begin
          sum_r = i_data_a + i_data_b;
          o_data_w = sum_r[11:0];
          o_valid_w = 1'b1;
          o_overflow_w = (i_data_a[11] == i_data_b[11]) && (sum_r[11] != i_data_a[11]);
        end  // ADD

        3'b001: begin
          diff_r = i_data_a - i_data_b;
          o_data_w = diff_r[11:0];
          o_valid_w = 1'b1;
          o_overflow_w = (i_data_a[11] != i_data_b[11]) && (i_data_a[11] != diff_r[11]);
        end  // SUBTRACT

        3'b010: begin
          mult_result_r = i_data_a * i_data_b;
          fixed_format_r = {{12{mult_result_r[16]}}, mult_result_r[16:5]};  //sign extend and shift by 5
          o_data_w = fixed_format_r[11:0];
          o_valid_w = 1'b1;
          o_overflow_w = ({12{fixed_format_r[11]}} != fixed_format_r[23:12]);
        end  // MULTIPLY

        3'b011: begin
          mac_mult_result_r = i_data_a * i_data_b;
          mac_fixed_format_r = {{12{mac_mult_result_r[16]}}, mac_mult_result_r[16:5]};
          // mac_mult_overflow_w = ({12{fixed_format_r[11]}} != fixed_format_r[23:12]);
          accumulator_r = prev_accumulator_r + mac_fixed_format_r;
          o_data_w = accumulator_r[11:0];
          o_valid_w = 1'b1;
          o_overflow_w = ({12{accumulator_r[11]}} != mac_fixed_format_r[23:12]);
        end  // MAC

        3'b100: begin
          o_data_w  = ~(i_data_a ^ i_data_b);
          o_valid_w = 1'b1;
        end  // XNOR

        3'b101: begin
          o_data_w  = (i_data_a[11] == 0) ? i_data_a : 12'd0;
          o_valid_w = 1'b1;
        end  // ReLU

        3'b110: begin
          mean_r = i_data_a + i_data_b;
          o_data_w = mean_r >> 1;
          o_valid_w = 1'b1;
        end  // MEAN

        3'b111: begin
          abs_a_r = (i_data_a[11] == 1'b1) ? (~i_data_a + 1) : i_data_a;
	  abs_b_r = (i_data_b[11] == 1'b1) ? (~i_data_b + 1) : i_data_b; 
          o_data_w  = (abs_a_r > abs_b_r) ? abs_a_r : abs_b_r;
          o_valid_w = 1'b1;
        end  // ABSOLUTE MAX

        default: begin
          o_data_w = 12'b0;
          o_valid_w = 1'b0;
          o_overflow_w = 1'b0;
        end  // Default case

      endcase
    end
  end

  // ---------------------------------------------------------------------------
  // Sequential Block
  // ---------------------------------------------------------------------------
  // ---- Write your sequential block design here ---- //

  always @(negedge i_clk or negedge i_rst_n) begin
    if (!i_rst_n) begin
      o_data_r <= 0;
      o_overflow_r <= 0;
      o_valid_r <= 0;
      prev_accumulator_r <= 0;
    end else begin
      o_data_r <= o_data_w;
      o_overflow_r <= o_overflow_w;
      o_valid_r <= o_valid_w;
      prev_accumulator_r <= accumulator_r;
    end
  end
endmodule

1101_hw1/testbench.v
`timescale 1ns/1ps
`define CYCLE       10.0
`define RST_DELAY   2
`define MAX_CYCLE   100000

`ifdef I0
    `define Inst_I  "./pattern/INST0_I.dat"
    `define Inst_O  "./pattern/INST0_O.dat"
    `define PAT_NUM 20
`elsif I1
    `define Inst_I  "./pattern/INST1_I.dat"
    `define Inst_O  "./pattern/INST1_O.dat"
    `define PAT_NUM 20
`elsif I2
    `define Inst_I  "./pattern/INST2_I.dat"
    `define Inst_O  "./pattern/INST2_O.dat"
    `define PAT_NUM 20
`elsif I3
    `define Inst_I  "./pattern/INST3_I.dat"
    `define Inst_O  "./pattern/INST3_O.dat"
    `define PAT_NUM 5
`elsif I4
    `define Inst_I  "./pattern/INST4_I.dat"
    `define Inst_O  "./pattern/INST4_O.dat"
    `define PAT_NUM 20
`elsif I5
    `define Inst_I  "./pattern/INST5_I.dat"
    `define Inst_O  "./pattern/INST5_O.dat"
    `define PAT_NUM 20
`elsif I6
    `define Inst_I  "./pattern/INST6_I.dat"
    `define Inst_O  "./pattern/INST6_O.dat"
    `define PAT_NUM 20
`elsif I7
    `define Inst_I  "./pattern/INST7_I.dat"
    `define Inst_O  "./pattern/INST7_O.dat"
    `define PAT_NUM 20
`elsif I8
    `define Inst_I  "./pattern/INST8_I.dat"
    `define Inst_O  "./pattern/INST8_O.dat"
    `define PAT_NUM 20
`else
    `define Inst_I  ""
    `define Inst_O  ""
    `define PAT_NUM 0
`endif




module tb;

    parameter INT_W  = 7;
    parameter FRAC_W = 5;
    parameter INST_W = 3;
    parameter DATA_W = INT_W + FRAC_W;

    reg                      i_clk;
    reg                      i_rst_n;
    reg                      i_valid;
    reg  signed [DATA_W-1:0] i_data_a;
    reg  signed [DATA_W-1:0] i_data_b;
    reg         [INST_W-1:0] i_inst;
    wire                     o_valid;
    wire signed [DATA_W-1:0] o_data;
    wire                     o_overflow;
    integer            i;
    integer            j;
    integer error;

    reg [2*DATA_W+INST_W-1:0] inst_idata [0:`PAT_NUM-1];
    reg [(DATA_W+1)-1:0]      inst_odata [0:`PAT_NUM-1];

    reg signed [DATA_W-1:0] test_inA  ;
    reg signed [DATA_W-1:0] test_inB  ;
    reg        [INST_W-1:0] test_inst ;
    reg                     test_outO ;
    reg signed [DATA_W-1:0] test_outD ;


    initial begin
        $readmemb(`Inst_I, inst_idata);
        $readmemb(`Inst_O, inst_odata);
    end


    alu u_alu (
        .i_clk          (i_clk      ),
        .i_rst_n        (i_rst_n    ),
        .i_valid        (i_valid    ),
        .i_data_a       (i_data_a   ),
        .i_data_b       (i_data_b   ),
        .i_inst         (i_inst     ),
        .o_valid        (o_valid    ),
        .o_data         (o_data     ),
        .o_overflow     (o_overflow )    
    );

    initial i_clk = 0;
    always #(`CYCLE/2.0) i_clk = ~i_clk; 
    initial begin
        $dumpfile("tb.vcd");
        $dumpvars(0, tb);
    end

    initial begin
        i        = 0;
        i_rst_n  = 1;
        i_valid  = 0;
        i_data_a = 0;
        i_data_b = 0;
        i_inst   = 0;
        reset;

        while (i < `PAT_NUM) begin
            @(negedge i_clk);
            i_valid = $random;
	    if (i_valid) begin
            	i_data_a = inst_idata[i][DATA_W-1          : 0];
            	i_data_b = inst_idata[i][2*DATA_W-1        : DATA_W];
            	i_inst   = inst_idata[i][2*DATA_W+INST_W-1 : 2*DATA_W+INST_W-3];
            	i = i + 1;
	    end
        end
        @(negedge i_clk);
	i_valid = 0;
    end

    initial begin
        j = 0;
        error = 0;
        while (j < `PAT_NUM) begin
            @(negedge i_clk);
            if (o_valid) begin
                test_inA  =  inst_idata[j][DATA_W-1          : 0     ];
                test_inB  =  inst_idata[j][2*DATA_W-1        : DATA_W];
                test_inst =  inst_idata[j][2*DATA_W+INST_W-1 : 2*DATA_W+INST_W-3];
                test_outO =  inst_odata[j][DATA_W];
                test_outD =  inst_odata[j][DATA_W-1          : 0     ];
                if (test_outO !== o_overflow) begin
                    $display (
                        "Test[%d]: Error! Inst=%b, A=%b, B=%b, Out=(%b, %b), yours=(%b, %b)", 
                        j, test_inst, test_inA, test_inB, test_outO, test_outD, o_overflow, o_data
                    );
                    error = error+1;
                end else if (test_outO == 0 && test_outD !== o_data) begin
                    $display (
                        "Test[%d]: Error! Inst=%b, A=%b, B=%b, Out=(%b, %b), yours=(%b, %b)", 
                        j, test_inst, test_inA, test_inB, test_outO, test_outD, o_overflow, o_data
                    );      
                    error = error+1;        
                end else if ((test_outD == o_data || test_outO !== 0) && test_outO == o_overflow) begin
                     $display("Test[%d]: Correct!", j);
                end else begin
                    $display("Test[%d]: Unknown output!!, Out=(%b, %b), yours=(%b, %b)", j, test_outO, test_outD, o_overflow, o_data);
                    error = error+1;
                end
                j = j + 1;
            end
        end

        $display("Pattern: ", `Inst_I);

        if(error == 0) begin
            $display("----------------------------------------------");
            $display("-                 ALL PASS!                  -");
            $display("----------------------------------------------");
        end else begin
            $display("----------------------------------------------");
            $display("  Wrong! Total error: %d                      ", error);
            $display("----------------------------------------------");
        end
        # ( 2 * `CYCLE);
        $finish;
    end

    initial begin
        # (`MAX_CYCLE * `CYCLE);
        $display("----------------------------------------------");
        $display("Latency of your design is over 100000 cycles!!");
        $display("----------------------------------------------");
        $finish;
    end

    task reset; begin
        # ( 0.25 * `CYCLE);
        i_rst_n = 0;    
        # ((`RST_DELAY) * `CYCLE);
        i_rst_n = 1;    
    end endtask

endmodule

1101_hw1/tb.vcd
$date
    Feb  4, 2026  01:24:27
$end
$version
    TOOL:	xmsim(64)	24.03-s013
$end
$timescale
    1 ps
$end

$scope module tb $end
$var parameter 32 !    INT_W $end
$var parameter 32 "    FRAC_W $end
$var parameter 32 #    INST_W $end
$var parameter 32 $    DATA_W $end
$var reg       1 %    i_clk $end
$var reg       1 &    i_rst_n $end
$var reg       1 '    i_valid $end
$var reg      12 (    i_data_a [11:0] $end
$var reg      12 )    i_data_b [11:0] $end
$var reg       3 *    i_inst [2:0] $end
$var wire      1 +    o_valid  $end
$var wire     12 ,    o_data [11:0] $end
$var wire      1 -    o_overflow  $end
$var integer  32 .    i $end
$var integer  32 /    j $end
$var integer  32 0    error $end
$var reg      27 1    inst_idata[0] [26:0] $end
$var reg      27 2    inst_idata[1] [26:0] $end
$var reg      27 3    inst_idata[2] [26:0] $end
$var reg      27 4    inst_idata[3] [26:0] $end
$var reg      27 5    inst_idata[4] [26:0] $end
$var reg      27 6    inst_idata[5] [26:0] $end
$var reg      27 7    inst_idata[6] [26:0] $end
$var reg      27 8    inst_idata[7] [26:0] $end
$var reg      27 9    inst_idata[8] [26:0] $end
$var reg      27 :    inst_idata[9] [26:0] $end
$var reg      27 ;    inst_idata[10] [26:0] $end
$var reg      27 <    inst_idata[11] [26:0] $end
$var reg      27 =    inst_idata[12] [26:0] $end
$var reg      27 >    inst_idata[13] [26:0] $end
$var reg      27 ?    inst_idata[14] [26:0] $end
$var reg      27 @    inst_idata[15] [26:0] $end
$var reg      27 A    inst_idata[16] [26:0] $end
$var reg      27 B    inst_idata[17] [26:0] $end
$var reg      27 C    inst_idata[18] [26:0] $end
$var reg      27 D    inst_idata[19] [26:0] $end
$var reg      13 E    inst_odata[0] [12:0] $end
$var reg      13 F    inst_odata[1] [12:0] $end
$var reg      13 G    inst_odata[2] [12:0] $end
$var reg      13 H    inst_odata[3] [12:0] $end
$var reg      13 I    inst_odata[4] [12:0] $end
$var reg      13 J    inst_odata[5] [12:0] $end
$var reg      13 K    inst_odata[6] [12:0] $end
$var reg      13 L    inst_odata[7] [12:0] $end
$var reg      13 M    inst_odata[8] [12:0] $end
$var reg      13 N    inst_odata[9] [12:0] $end
$var reg      13 O    inst_odata[10] [12:0] $end
$var reg      13 P    inst_odata[11] [12:0] $end
$var reg      13 Q    inst_odata[12] [12:0] $end
$var reg      13 R    inst_odata[13] [12:0] $end
$var reg      13 S    inst_odata[14] [12:0] $end
$var reg      13 T    inst_odata[15] [12:0] $end
$var reg      13 U    inst_odata[16] [12:0] $end
$var reg      13 V    inst_odata[17] [12:0] $end
$var reg      13 W    inst_odata[18] [12:0] $end
$var reg      13 X    inst_odata[19] [12:0] $end
$var reg      12 Y    test_inA [11:0] $end
$var reg      12 Z    test_inB [11:0] $end
$var reg       3 [    test_inst [2:0] $end
$var reg       1 \    test_outO $end
$var reg      12 ]    test_outD [11:0] $end

$scope module u_alu $end
$var wire      1 ^    i_clk  $end
$var wire      1 _    i_rst_n  $end
$var wire      1 `    i_valid  $end
$var wire     12 a    i_data_a [11:0] $end
$var wire     12 b    i_data_b [11:0] $end
$var wire      3 c    i_inst [2:0] $end
$var wire      1 +    o_valid  $end
$var wire     12 ,    o_data [11:0] $end
$var wire      1 -    o_overflow  $end
$var reg      12 d    o_data_w [11:0] $end
$var reg      12 e    o_data_r [11:0] $end
$var reg       1 f    o_valid_w $end
$var reg       1 g    o_valid_r $end
$var reg       1 h    o_overflow_w $end
$var reg       1 i    o_overflow_r $end
$var reg      12 j    abs_a_r [11:0] $end
$var reg      12 k    abs_b_r [11:0] $end
$var reg      13 l    mean_r [12:0] $end
$var reg      13 m    sum_r [12:0] $end
$var reg      13 n    diff_r [12:0] $end
$var reg      24 o    mult_result_r [23:0] $end
$var reg      24 p    mac_mult_result_r [23:0] $end
$var reg      24 q    fixed_format_r [23:0] $end
$var reg      24 r    mac_fixed_format_r [23:0] $end
$var reg      25 s    prev_accumulator_r [24:0] $end
$var reg      25 t    accumulator_r [24:0] $end
$upscope $end

$upscope $end

$enddefinitions $end
$dumpvars
b1100 $
b11 #
b101 "
b111 !
0%
1&
0'
b0 (
b0 )
b0 *
x+
bx ,
x-
b0 .
b0 /
b0 0
b111001100000100000000110101 1
b10101001111110000000101001 2
b10111101111010101111011011 3
b11111101100010000001100000 4
b11111101101111000000111111 5
b11111111101011111100111001 6
b10101110010011000000 7
b1110011100101111101010001 8
b110110110000110110000101100 9
b110001000000101101011100101 :
b101100000110000011110100101 ;
b11111101111101000000111011 <
b11000011101000000001000100 =
b11111110101010111110000100 >
b11111111110000111100001110 ?
b11111100001011111100111100 @
b11000011001111000011001011 A
b100111101110010100100100001 B
b111010101000110100011010101 C
b101011000000110001100100 D
b1100000100 E
b100011110001 F
b1100010101101 G
b111000100110 H
b110100001001 I
b110110001100 J
b10101101110 K
b1001101100 L
b110011011001 M
b111001110101 N
b11110100101 O
b111100001110 P
b11111011 Q
b1001001000 R
b1011000001 S
b1100010011110 T
b1110110111111 U
b100110101100 V
b11100101011 W
b1011100100100 X
bx Y
bx Z
bx [
x\
bx ]
0^
1_
0`
b0 a
b0 b
b0 c
bx d
bx e
0f
xg
0h
xi
bx j
bx k
bx l
bx m
bx n
bx o
bx p
bx q
bx r
bx s
bx t
$end
#2500
0&
0_
b0 e
0i
0g
b0 s
0+
0-
b0 ,
#5000
1%
1^
#10000
0%
0^
#15000
1%
1^
#20000
0%
0^
#22500
1&
1_
#25000
1%
1^
#30000
0%
0^
bx e
bx s
bx ,
#35000
1%
1^
#40000
0%
1'
b110101 (
b1100000100 )
b111 *
b1 .
b111 c
b1100000100 b
b110101 a
1`
0^
b0 s
b110101 j
b1100000100 k
b1100000100 d
1f
b1100000100 e
1g
bx s
0f
b0 s
1f
1+
b1100000100 ,
#45000
1%
1^
#50000
0%
b110101 Y
b1100000100 Z
b111 [
0\
b1100000100 ]
b1 /
b101001 (
b101001111110 )
b10 *
b10 .
b10 c
b101001111110 b
b101001 a
0^
0f
b111111110001111000101110 o
b111111111111100011110001 q
b100011110001 d
1f
b100011110001 e
bx s
0f
b0 s
1f
b100011110001 ,
#55000
1%
1^
#60000
0%
b101001 Y
b101001111110 Z
b10 [
b100011110001 ]
b10 /
b101111011011 (
b111101111010 )
b11 .
b111101111010 b
b101111011011 a
0^
0f
b100010101101011110 o
b101011010 q
b101011010 d
1f
b101011010 e
bx s
0f
b0 s
1f
b101011010 ,
#65000
1%
1^
#70000
0%
b101111011011 Y
b111101111010 Z
1\
b100010101101 ]
b1 0
b11 /
b1100000 (
b111101100010 )
b11 *
b100 .
b11 c
b111101100010 b
b1100000 a
0^
0f
b111111111100010011000000 p
b111111111111111000100110 r
b1111111111111111000100110 t
b111000100110 d
1f
b111000100110 e
b1111111111111111000100110 s
0f
b0 s
1f
b111000100110 ,
#75000
1%
1^
#80000
0%
b1100000 Y
b111101100010 Z
b11 [
0\
b111000100110 ]
b100 /
b111111 (
b111101101111 )
b101 .
b111101101111 b
b111111 a
0^
0f
b111111111101110001010001 p
b111111111111111011100010 r
b1111111111111111011100010 t
b111011100010 d
1f
b111011100010 e
b1111111111111111011100010 s
0f
b0 s
1f
b111011100010 ,
#85000
1%
1^
#90000
0%
b111111 Y
b111101101111 Z
b110100001001 ]
b10 0
b101 /
b111100111001 (
b111111101011 )
b110 .
b111111101011 b
b111100111001 a
0^
0f
b1000001010011 p
b10000010 r
b10000010 t
b10000010 d
1f
b10000010 e
b10000010 s
0f
b0 s
1f
b10000010 ,
#95000
1%
1^
#100000
0%
b111100111001 Y
b111111101011 Z
b110110001100 ]
b11 0
b110 /
0'
0`
0^
0f
0g
b10000010 s
0+
#105000
1%
1^
#110000
0%
1'
b10011000000 (
b10101110 )
b0 *
b111 .
b0 c
b10101110 b
b10011000000 a
1`
0^
b0 s
b10101101110 m
b10101101110 d
1f
b10101101110 e
1g
b10000010 s
0f
b0 s
1f
1+
b10101101110 ,
#115000
1%
1^
#120000
0%
b10011000000 Y
b10101110 Z
b0 [
b10101101110 ]
b111 /
b111101010001 (
b110011100101 )
b1 *
b1000 .
b1 c
b110011100101 b
b111101010001 a
0^
0f
b1001101100 n
b1001101100 d
1f
b1001101100 e
b10000010 s
0f
b0 s
1f
b1001101100 ,
#125000
1%
1^
#130000
0%
b111101010001 Y
b110011100101 Z
b1 [
b1001101100 ]
b1000 /
0'
0`
0^
0f
0g
b10000010 s
0+
#135000
1%
1^
#140000
0%
1'
b110000101100 (
b110110000110 )
b110 *
b1001 .
b110 c
b110110000110 b
b110000101100 a
1`
0^
b0 s
b1100110110010 l
b110011011001 d
1f
b110011011001 e
1g
b10000010 s
0f
b0 s
1f
1+
b110011011001 ,
#145000
1%
1^
#150000
0%
b110000101100 Y
b110110000110 Z
b110 [
b110011011001 ]
b1001 /
b101011100101 (
b1000000101 )
b1010 .
b1000000101 b
b101011100101 a
0^
0f
b1110011101010 l
b111001110101 d
1f
b111001110101 e
b10000010 s
0f
b0 s
1f
b111001110101 ,
#155000
1%
1^
#160000
0%
b101011100101 Y
b1000000101 Z
b111001110101 ]
b1010 /
0'
0`
0^
0f
0g
b10000010 s
0+
#165000
1%
1^
#170000
0%
1'
b11110100101 (
b100000110000 )
b101 *
b1011 .
b101 c
b100000110000 b
b11110100101 a
1`
0^
b0 s
b11110100101 d
1f
b11110100101 e
1g
b10000010 s
0f
b0 s
1f
1+
b11110100101 ,
#175000
1%
1^
#180000
0%
b11110100101 Y
b100000110000 Z
b101 [
b11110100101 ]
b1011 /
0'
0`
0^
0f
0g
b10000010 s
0+
#185000
1%
1^
#190000
0%
1'
b111011 (
b111101111101 )
b11 *
b1100 .
b11 c
b111101111101 b
b111011 a
1`
0^
b0 s
b111111111110000111001111 p
b111111111111111100001110 r
b1111111111111111100001110 t
b111100001110 d
1f
b111100001110 e
1g
b1111111111111111100001110 s
0f
b0 s
1f
1+
b111100001110 ,
#195000
1%
1^
#200000
0%
b111011 Y
b111101111101 Z
b11 [
b111100001110 ]
b1100 /
0'
0`
0^
0f
0g
b1111111111111111100001110 s
0+
#205000
1%
1^
#210000
0%
1'
b1000100 (
b11101000 )
b1101 .
b11101000 b
b1000100 a
1`
0^
b0 s
b11110110100000 p
b111101101 r
b111101101 t
b111101101 d
1f
b111101101 e
1g
b111101101 s
0f
b0 s
1f
1+
b111101101 ,
#215000
1%
1^
#220000
0%
b1000100 Y
b11101000 Z
b11111011 ]
b100 0
b1101 /
b111110000100 (
b111110101010 )
b1110 .
b111110101010 b
b111110000100 a
0^
0f
b10100110101000 p
b101001101 r
b101001101 t
b101001101 d
1f
b101001101 e
b101001101 s
0f
b0 s
1f
b101001101 ,
#225000
1%
1^
#230000
0%
b111110000100 Y
b111110101010 Z
b1001001000 ]
b101 0
b1110 /
0'
0`
0^
0f
0g
b101001101 s
0+
#235000
1%
1^
#240000
0%
1'
b111100001110 (
b111111110000 )
b1111 .
b111111110000 b
b111100001110 a
1`
0^
b0 s
b111100100000 p
b1111001 r
b1111001 t
b1111001 d
1f
b1111001 e
1g
b1111001 s
0f
b0 s
1f
1+
b1111001 ,
#245000
1%
1^
#250000
0%
b111100001110 Y
b111111110000 Z
b1011000001 ]
b110 0
b1111 /
0'
0`
0^
0f
0g
b1111001 s
0+
#255000
1%
1^
#260000
0%
0^
#265000
1%
1^
#270000
0%
0^
#275000
1%
1^
#280000
0%
1'
b111100111100 (
b111100001011 )
b10000 .
b111100001011 b
b111100111100 a
1`
0^
b0 s
b1011101110010100 p
b10111011100 r
b10111011100 t
b10111011100 d
1f
b10111011100 e
1g
b10111011100 s
0f
b0 s
1f
1+
b10111011100 ,
#285000
1%
1^
#290000
0%
b111100111100 Y
b111100001011 Z
1\
b100010011110 ]
b111 0
b10000 /
0'
0`
0^
0f
0g
b10111011100 s
0+
#295000
1%
1^
#300000
0%
1'
b11001011 (
b11001111 )
b10001 .
b11001111 b
b11001011 a
1`
0^
b0 s
b1010010000100101 p
b10100100001 r
b10100100001 t
b10100100001 d
1f
b10100100001 e
1g
b10100100001 s
0f
b0 s
1f
1+
b10100100001 ,
#305000
1%
1^
#310000
0%
b11001011 Y
b11001111 Z
b110110111111 ]
b1000 0
b10001 /
b100100100001 (
b111101110010 )
b100 *
b10010 .
b100 c
b111101110010 b
b100100100001 a
0^
0f
b100110101100 d
1f
b100110101100 e
b10100100001 s
0f
b0 s
1f
b100110101100 ,
#315000
1%
1^
#320000
0%
b100100100001 Y
b111101110010 Z
b100 [
0\
b100110101100 ]
b10010 /
b100011010101 (
b10101000110 )
b111 *
b10011 .
b111 c
b10101000110 b
b100011010101 a
0^
0f
b11100101011 j
b10101000110 k
b11100101011 d
1f
b11100101011 e
b10100100001 s
0f
b0 s
1f
b11100101011 ,
#325000
1%
1^
#330000
0%
b100011010101 Y
b10101000110 Z
b111 [
b11100101011 ]
b10011 /
b110001100100 (
b101011000000 )
b0 *
b10100 .
b0 c
b101011000000 b
b110001100100 a
0^
0f
b1011100100100 m
b11100100100 d
1f
1h
b11100100100 e
1i
b10100100001 s
0f
0h
b0 s
1f
1h
1-
b11100100100 ,
#335000
1%
1^
#340000
0%
b110001100100 Y
b101011000000 Z
b0 [
1\
b11100100100 ]
b10100 /
0'
0`
0^
0f
0h
0i
0g
b10100100001 s
0+
0-
